wxbreads/__init__.py
wxbreads/base.py
wxbreads/images.py
wxbreads/login.py
wxbreads/trayicon.py
wxbreads/utils.py
wxbreads/widgets.py
wxbreads-2023.7.26.dist-info/LICENSE
wxbreads-2023.7.26.dist-info/METADATA
wxbreads-2023.7.26.dist-info/WHEEL
wxbreads-2023.7.26.dist-info/top_level.txt
wxbreads-2023.7.26.dist-info/RECORD
