Metadata-Version: 2.1
Name: wxbreads
Version: 2023.7.26
Summary: Small handy snippets of wxpython
Home-page: https://github.com/lixxu/wxbreads
Author: Lix Xu
Author-email: xuzenglin@gmail.com
License: BSD
Platform: any
Classifier: Environment :: Console
Classifier: Intended Audience :: Developers
Classifier: License :: OSI Approved :: BSD License
Classifier: Operating System :: OS Independent
Classifier: Topic :: Software Development :: Libraries :: Python Modules
Classifier: Programming Language :: Python
Classifier: Programming Language :: Python :: 2
Classifier: Programming Language :: Python :: 3
License-File: LICENSE
Requires-Dist: six
